DTWpy/__init__.py
DTWpy/distance_measure.py
DTWpy/dtwpy.py
DTWpy/patterns.py
DTWpy/plotDTWalignment.py
DTWpy-0.1.0.dist-info/DESCRIPTION.rst
DTWpy-0.1.0.dist-info/METADATA
DTWpy-0.1.0.dist-info/RECORD
DTWpy-0.1.0.dist-info/WHEEL
DTWpy-0.1.0.dist-info/metadata.json
DTWpy-0.1.0.dist-info/top_level.txt
