Metadata-Version: 2.0
Name: DTWpy
Version: 0.1.0
Summary: Module for Computing and Visualizing Dynamic Time Warping Alignment
Home-page: https://github.com/gulzi/DTWpy
Author: Hafiz Muhammad Gulzar
Author-email: hmgulzar88@gmail.com
License: MIT
Keywords: DTWpy,Module for Computing and Visualizing Dynamic Time Warping Alignment,Hafiz Muhammad Gulzar
Platform: UNKNOWN
Classifier: Development Status :: 3 - Alpha
Classifier: License :: OSI Approved :: MIT License
Classifier: Programming Language :: Python :: 2
Classifier: Programming Language :: Python :: 2.7
Classifier: Programming Language :: Python :: 3
Classifier: Programming Language :: Python :: 3.6
Requires-Dist: matplotlib (==1.4.3)
Requires-Dist: memprof (==0.3.4)
Requires-Dist: numpy (==1.9.2)
